tgm/__init__.py
tgm/constants.py
tgm/exceptions.py
tgm/core/__init__.py
tgm/core/batch.py
tgm/core/graph.py
tgm/core/timedelta.py
tgm/core/_storage/__init__.py
tgm/core/_storage/base.py
tgm/core/_storage/backends/__init__.py
tgm/core/_storage/backends/array_backend.py
tgm/data/__init__.py
tgm/data/dg_data.py
tgm/data/loader.py
tgm/data/split.py
tgm/hooks/__init__.py
tgm/hooks/base.py
tgm/hooks/batch_analytics.py
tgm/hooks/dedup.py
tgm/hooks/device.py
tgm/hooks/hook_manager.py
tgm/hooks/negatives.py
tgm/hooks/neighbors.py
tgm/hooks/node_analytics.py
tgm/hooks/node_tracks.py
tgm/hooks/recipe.py
tgm/nn/__init__.py
tgm/nn/decoder/__init__.py
tgm/nn/decoder/graphproppred.py
tgm/nn/decoder/linkproppred.py
tgm/nn/decoder/ncnpred.py
tgm/nn/decoder/nodeproppred.py
tgm/nn/encoder/__init__.py
tgm/nn/encoder/ctan.py
tgm/nn/encoder/dygformer.py
tgm/nn/encoder/gclstm.py
tgm/nn/encoder/roland.py
tgm/nn/encoder/tgcn.py
tgm/nn/encoder/tgn.py
tgm/nn/encoder/tpnet.py
tgm/nn/modules/__init__.py
tgm/nn/modules/attention.py
tgm/nn/modules/edgebank.py
tgm/nn/modules/mlp_mixer.py
tgm/nn/modules/poptrack.py
tgm/nn/modules/t_comem.py
tgm/nn/modules/time_encoding.py
tgm/util/__init__.py
tgm/util/logging.py
tgm/util/seed.py
tgm_lib-0.1.0b1.dist-info/licenses/LICENSE
tgm_lib-0.1.0b1.dist-info/WHEEL
tgm_lib-0.1.0b1.dist-info/METADATA
tgm_lib-0.1.0b1.dist-info/RECORD
