Metadata-Version: 2.4
Name: tgm-lib
Version: 0.1.0b1
Summary: Efficient and Modular ML on Temporal Graphs
Author-email: Jacob Chmura <jacobpaul.chmura@gmail.com>, Shenyang Huang <shenyang.huang@mail.mcgill.ca>
Requires-Python: >=3.10
License-File: LICENSE
Requires-Dist: numpy>=2.2.6
Requires-Dist: torch>=2.5.1
Requires-Dist: torch-geometric>=2.6.1
